rabbit_library/__init__.py
rabbit_library/Rabbit.py
rabbit_library-1.0.11.dist-info/METADATA
rabbit_library-1.0.11.dist-info/WHEEL
rabbit_library-1.0.11.dist-info/RECORD
