Metadata-Version: 2.1
Name: rabbit-library
Version: 1.0.11
Summary: Biblioteca para se conectar ao rabbit e possibilitar trabalhar com o serviço de mensageria
License: MIT
Author: Eliézer Schwartz
Author-email: eliezer.mail090@gmail.com
Requires-Python: >=3.11,<4.0
Classifier: Development Status :: 5 - Production/Stable
Classifier: Environment :: Console
Classifier: License :: OSI Approved :: MIT License
Classifier: Natural Language :: Portuguese (Brazilian)
Classifier: Programming Language :: Python :: 3
Classifier: Programming Language :: Python :: 3.11
Classifier: Programming Language :: Python :: 3.11
Requires-Dist: pika (==1.3.2)
